cvehound/__init__.py
cvehound/__main__.py
cvehound/config.py
cvehound/cwe.py
cvehound/exception.py
cvehound/kbuild.py
cvehound/util.py
cvehound/cve/CVE-2013-2930.cocci
cvehound/cve/CVE-2013-6383.cocci
cvehound/cve/CVE-2014-0049.cocci
cvehound/cve/CVE-2014-0100.cocci
cvehound/cve/CVE-2014-0101.cocci
cvehound/cve/CVE-2014-0155.cocci
cvehound/cve/CVE-2014-1737.cocci
cvehound/cve/CVE-2014-1738.cocci
cvehound/cve/CVE-2014-1874.cocci
cvehound/cve/CVE-2014-5077.cocci
cvehound/cve/CVE-2014-7841.cocci
cvehound/cve/CVE-2014-7975.cocci
cvehound/cve/CVE-2014-8480.cocci
cvehound/cve/CVE-2014-8481.cocci
cvehound/cve/CVE-2014-8709.cocci
cvehound/cve/CVE-2014-9715.cocci
cvehound/cve/CVE-2014-9903.cocci
cvehound/cve/CVE-2014-9904.cocci
cvehound/cve/CVE-2015-1339.cocci
cvehound/cve/CVE-2015-1421.cocci
cvehound/cve/CVE-2015-1593.cocci
cvehound/cve/CVE-2015-3636.cocci
cvehound/cve/CVE-2015-4004.cocci
cvehound/cve/CVE-2015-4700.cocci
cvehound/cve/CVE-2015-7566.cocci
cvehound/cve/CVE-2015-8746.cocci
cvehound/cve/CVE-2015-8785.cocci
cvehound/cve/CVE-2015-8787.cocci
cvehound/cve/CVE-2015-8961.cocci
cvehound/cve/CVE-2016-10150.cocci
cvehound/cve/CVE-2016-10764.cocci
cvehound/cve/CVE-2016-10907.cocci
cvehound/cve/CVE-2016-2070.cocci
cvehound/cve/CVE-2016-2117.cocci
cvehound/cve/CVE-2016-2383.cocci
cvehound/cve/CVE-2016-2384.cocci
cvehound/cve/CVE-2016-2782.cocci
cvehound/cve/CVE-2016-3713.cocci
cvehound/cve/CVE-2016-4470.cocci
cvehound/cve/CVE-2016-4568.cocci
cvehound/cve/CVE-2016-4805.cocci
cvehound/cve/CVE-2016-5195.cocci
cvehound/cve/CVE-2016-5828.cocci
cvehound/cve/CVE-2016-6156.cocci
cvehound/cve/CVE-2016-6162.cocci
cvehound/cve/CVE-2016-6516.cocci
cvehound/cve/CVE-2016-6828.cocci
cvehound/cve/CVE-2016-7913.cocci
cvehound/cve/CVE-2016-8399.cocci
cvehound/cve/CVE-2016-8630.cocci
cvehound/cve/CVE-2016-8650.cocci
cvehound/cve/CVE-2016-9191.cocci
cvehound/cve/CVE-2016-9754.cocci
cvehound/cve/CVE-2016-9793.cocci
cvehound/cve/CVE-2016-9919.cocci
cvehound/cve/CVE-2017-1000112.cocci
cvehound-1.2.1.dist-info/LICENSE
cvehound-1.2.1.dist-info/METADATA
cvehound-1.2.1.dist-info/WHEEL
cvehound-1.2.1.dist-info/entry_points.txt
cvehound-1.2.1.dist-info/top_level.txt
cvehound-1.2.1.dist-info/RECORD
