Metadata-Version: 2.1
Name: cvehound
Version: 1.2.1
Summary: A tool to check linux kernel source dump for known CVEs
Home-page: http://github.com/evdenis/cvehound
Author: Denis Efremov
Author-email: efremov@linux.com
License: GPLv3
Keywords: cve,linux,kernel,spatch,cve-scanning,coccinelle
Classifier: License :: OSI Approved :: GNU General Public License v3 (GPLv3)
Classifier: Operating System :: POSIX :: Linux
Classifier: Operating System :: MacOS :: MacOS X
Classifier: Programming Language :: Python :: 3
Classifier: Programming Language :: Python :: 3.5
Classifier: Programming Language :: Python :: 3.6
Classifier: Programming Language :: Python :: 3.7
Classifier: Programming Language :: Python :: 3.8
Classifier: Programming Language :: Python :: 3.9
Classifier: Programming Language :: Python :: 3.10
Classifier: Programming Language :: Python :: 3.11
Requires-Python: >=3.5
License-File: LICENSE
Requires-Dist: sympy
Requires-Dist: lxml
Provides-Extra: tests
Requires-Dist: pytest ; extra == 'tests'
Requires-Dist: gitpython ; extra == 'tests'
Requires-Dist: psutil ; extra == 'tests'
